odoo/addons/account_invoice_origin_link/README.rst
odoo/addons/account_invoice_origin_link/__init__.py
odoo/addons/account_invoice_origin_link/__manifest__.py
odoo/addons/account_invoice_origin_link/i18n/account_invoice_origin_link.pot
odoo/addons/account_invoice_origin_link/i18n/it.po
odoo/addons/account_invoice_origin_link/models/__init__.py
odoo/addons/account_invoice_origin_link/models/account_move.py
odoo/addons/account_invoice_origin_link/readme/CONTRIBUTORS.rst
odoo/addons/account_invoice_origin_link/readme/DESCRIPTION.rst
odoo/addons/account_invoice_origin_link/static/description/icon.png
odoo/addons/account_invoice_origin_link/static/description/index.html
odoo/addons/account_invoice_origin_link/views/account_move_views.xml
odoo14_addon_account_invoice_origin_link-14.0.1.0.1.dev3.dist-info/METADATA
odoo14_addon_account_invoice_origin_link-14.0.1.0.1.dev3.dist-info/WHEEL
odoo14_addon_account_invoice_origin_link-14.0.1.0.1.dev3.dist-info/top_level.txt
odoo14_addon_account_invoice_origin_link-14.0.1.0.1.dev3.dist-info/RECORD
